{
  "project_info": {
    "project_number": "165374914153",
    "project_id": "todo-app-project-e81a3",
    "storage_bucket": "todo-app-project-e81a3.appspot.com"
  },
  "client": [
    {
      "client_info": {
        "mobilesdk_app_id": "1:165374914153:android:c662f8bc9ec673adf2fcf8",
        "android_client_info": {
          "package_name": "com.example.todoapp"
        }
      },
      "oauth_client": [],
      "api_key": [
        {
          "current_key": "AIzaSyD8Ikqw7I6cAH3l-AmE2o2qAnx2jhPQ_WI"
        }
      ],
      "services": {
        "appinvite_service": {
          "other_platform_oauth_client": []
        }
      }
    }
  ],
  "configuration_version": "1"
}